gaqqie_door/__init__.py
gaqqie_door/adaptor/__init__.py
gaqqie_door/adaptor/qiskit/__init__.py
gaqqie_door/adaptor/qiskit/gaqqie_backend.py
gaqqie_door/adaptor/qiskit/gaqqie_job.py
gaqqie_door/adaptor/qiskit/gaqqie_provider.py
gaqqie_door/rest/__init__.py
gaqqie_door/rest/api_client.py
gaqqie_door/rest/api_client2.py
gaqqie_door/rest/configuration.py
gaqqie_door/rest/rest.py
gaqqie_door/rest/api/__init__.py
gaqqie_door/rest/api/device_api.py
gaqqie_door/rest/api/job_api.py
gaqqie_door/rest/api/provider_api.py
gaqqie_door/rest/models/__init__.py
gaqqie_door/rest/models/device.py
gaqqie_door/rest/models/job.py
gaqqie_door/rest/models/jobbeforesubmission.py
gaqqie_door/rest/models/provider.py
gaqqie_door/rest/models/result.py
tests/__init__.py
tests/gaqqie_door/__init__.py
tests/gaqqie_door/adaptor/__init__.py
tests/gaqqie_door/adaptor/qiskit/__init__.py
tests/gaqqie_door/adaptor/qiskit/test_gaqqie_provider.py
gaqqie_door-0.2.0.dist-info/LICENSE
gaqqie_door-0.2.0.dist-info/METADATA
gaqqie_door-0.2.0.dist-info/WHEEL
gaqqie_door-0.2.0.dist-info/top_level.txt
gaqqie_door-0.2.0.dist-info/RECORD
